nltk_tgrep/__init__.py
nltk_tgrep/tgrep.py
nltk_tgrep/VERSION
nltk_tgrep/tests/__init__.py
nltk_tgrep/tests/test_tgrep.py
nltk_tgrep-1.0.6.dist-info/DESCRIPTION.rst
nltk_tgrep-1.0.6.dist-info/METADATA
nltk_tgrep-1.0.6.dist-info/metadata.json
nltk_tgrep-1.0.6.dist-info/RECORD
nltk_tgrep-1.0.6.dist-info/top_level.txt
nltk_tgrep-1.0.6.dist-info/WHEEL
