Metadata-Version: 1.1
Name: nltk_tgrep
Version: 1.0.6
Summary: tgrep2 Searching for NLTK Trees
Home-page: https://github.com/wroberts/nltk_tgrep
Author: Will Roberts
Author-email: wildwilhelm@gmail.com
License: MIT
Keywords: nltk tgrep tgrep2 tree search
Platform: UNKNOWN
Classifier: Development Status :: 3 - Alpha
Classifier: Intended Audience :: Developers
Classifier: Intended Audience :: Science/Research
Classifier: Topic :: Scientific/Engineering
Classifier: Topic :: Text Processing :: Linguistic
Classifier: License :: OSI Approved :: MIT License
Classifier: Programming Language :: Python :: 2
Classifier: Programming Language :: Python :: 2.6
Classifier: Programming Language :: Python :: 2.7
Classifier: Programming Language :: Python :: 3
Classifier: Programming Language :: Python :: 3.2
Classifier: Programming Language :: Python :: 3.3
Classifier: Programming Language :: Python :: 3.4
